evrmore_accounts/__init__.py
evrmore_accounts/api.py
evrmore_accounts/app.py
evrmore_accounts/api/__init__.py
evrmore_accounts/api/auth.py
evrmore_accounts/api/server.py
evrmore_accounts/static/accounts.css
evrmore_accounts/static/evrmore-accounts.js
evrmore_accounts/static/evrmore-logo.svg
evrmore_accounts/static/style.css
evrmore_accounts/templates/demo.html
evrmore_accounts/templates/docs.html
evrmore_accounts/templates/example.html
evrmore_accounts/templates/index.html
evrmore_accounts-1.0.0.dist-info/LICENSE
evrmore_accounts-1.0.0.dist-info/METADATA
evrmore_accounts-1.0.0.dist-info/WHEEL
evrmore_accounts-1.0.0.dist-info/top_level.txt
evrmore_accounts-1.0.0.dist-info/RECORD
